MANIFEST.in
README.rst
setup.py
NoseGrowlNotify.egg-info/PKG-INFO
NoseGrowlNotify.egg-info/SOURCES.txt
NoseGrowlNotify.egg-info/dependency_links.txt
NoseGrowlNotify.egg-info/entry_points.txt
NoseGrowlNotify.egg-info/requires.txt
NoseGrowlNotify.egg-info/top_level.txt
nosegrowlnotify/__init__.py
nosegrowlnotify/dialog-error.png
nosegrowlnotify/dialog-ok.png