Metadata-Version: 1.0
Name: NoseGrowlNotify
Version: 0.1
Summary: nose plugin for Growl notifications
Home-page: http://github.org/fgmacedo/nose-growl-notify
Author: Fernando Macedo
Author-email: fgmacedo@gmail.com
License: Creative Commons Attribution license (CC BY)
Platform: UNKNOWN
